undetected_playwright/py.typed
undetected_playwright/__init__.py
undetected_playwright/__main__.py
undetected_playwright/async_api/_context_manager.py
undetected_playwright/async_api/_generated.py
undetected_playwright/async_api/__init__.py
undetected_playwright/driver/LICENSE
undetected_playwright/driver/node
undetected_playwright/driver/playwright.sh
undetected_playwright/driver/README.md
undetected_playwright/driver/package/api.json
undetected_playwright/driver/package/browsers.json
undetected_playwright/driver/package/cli.js
undetected_playwright/driver/package/index.d.ts
undetected_playwright/driver/package/index.js
undetected_playwright/driver/package/index.mjs
undetected_playwright/driver/package/LICENSE
undetected_playwright/driver/package/NOTICE
undetected_playwright/driver/package/package.json
undetected_playwright/driver/package/protocol.yml
undetected_playwright/driver/package/README.md
undetected_playwright/driver/package/ThirdPartyNotices.txt
undetected_playwright/driver/package/bin/install_media_pack.ps1
undetected_playwright/driver/package/bin/PrintDeps.exe
undetected_playwright/driver/package/bin/README.md
undetected_playwright/driver/package/bin/reinstall_chrome_beta_linux.sh
undetected_playwright/driver/package/bin/reinstall_chrome_beta_mac.sh
undetected_playwright/driver/package/bin/reinstall_chrome_beta_win.ps1
undetected_playwright/driver/package/bin/reinstall_chrome_stable_linux.sh
undetected_playwright/driver/package/bin/reinstall_chrome_stable_mac.sh
undetected_playwright/driver/package/bin/reinstall_chrome_stable_win.ps1
undetected_playwright/driver/package/bin/reinstall_msedge_beta_linux.sh
undetected_playwright/driver/package/bin/reinstall_msedge_beta_mac.sh
undetected_playwright/driver/package/bin/reinstall_msedge_beta_win.ps1
undetected_playwright/driver/package/bin/reinstall_msedge_dev_linux.sh
undetected_playwright/driver/package/bin/reinstall_msedge_dev_mac.sh
undetected_playwright_patch-1.40.0.post1700587210000.dist-info/entry_points.txt
undetected_playwright_patch-1.40.0.post1700587210000.dist-info/LICENSE
undetected_playwright_patch-1.40.0.post1700587210000.dist-info/METADATA
undetected_playwright_patch-1.40.0.post1700587210000.dist-info/RECORD
undetected_playwright_patch-1.40.0.post1700587210000.dist-info/top_level.txt
undetected_playwright_patch-1.40.0.post1700587210000.dist-info/WHEEL
