Metadata-Version: 2.1
Name: undetected-playwright-patch
Version: 1.40.0.post1700587210000
Summary: Undetected version of playwright
Home-page: https://github.com/kaliiiiiiiiii/undetected-playwright-python
Author: Microsoft Corporation, patches by github.com/kaliiiiiiiiii
Author-email: 
License: Apache-2.0
Project-URL: Release notes, https://github.com/kaliiiiiiiiii/undetected-playwright-python/releases
Project-URL: Bug Reports, https://github.com/kaliiiiiiiiii/undetected-playwright-python/issues
Project-URL: Source Code, https://github.com/kaliiiiiiiiii/undetected-playwright-python/
Classifier: Topic :: Software Development :: Testing
Classifier: Topic :: Internet :: WWW/HTTP :: Browsers
Classifier: Intended Audience :: Developers
Classifier: Programming Language :: Python :: 3
Classifier: Programming Language :: Python :: 3.8
Classifier: Programming Language :: Python :: 3.9
Classifier: Programming Language :: Python :: 3.10
Classifier: Programming Language :: Python :: 3.11
Classifier: Programming Language :: Python :: 3.12
Classifier: License :: OSI Approved :: Apache Software License
Classifier: Operating System :: OS Independent
Requires-Python: >=3.8
License-File: LICENSE
Requires-Dist: greenlet ==3.0.1
Requires-Dist: pyee ==11.0.1
Requires-Dist: typing-extensions ; python_version <= "3.8"
